[
  {
    "name": "Attack on Titan Erwin Smith",
    "character": "Erwin Smith",
    "company": "Attack on Titan",
    "price": 1944,
    "dimensions": "36 cm",
    "material": "resina",
    "brand": "Bandai",
    "principalImage": "AOTfigure1-1.png",
    "images": ["AOTfigure1-2.png", "AOTfigure1-3.png", "AOTfigure1-4.png", "AOTfigure1-5.png"],
    "amount": 100,
    "animeName": "AttackOnTitan"
  },
  {
    "name": "Attack on Titan Levi Ackerman",
    "character": "Levi Ackerman",
    "company": "Attack on Titan",
    "price": 55,
    "dimensions": "36 cm",
    "material": "PVC",
    "brand": "Bandai",
    "principalImage": "AOTfigure2-1.png",
    "images": ["AOTfigure2-2.png", "AOTfigure2-3.png", "AOTfigure2-4.png", "AOTfigure2-5.png"],
    "amount": 100,
    "animeName": "AttackOnTitan"
  },
  {
    "name": "Attack on Titan Levi Renewal Package ARTFX J",
    "character": "Levi Ackerman",
    "company": "Attack on Titan",
    "price": 165,
    "dimensions": "28 cm",
    "material": "PVC",
    "brand": "Kotobukiya",
    "principalImage": "AOTfigure3-1.png",
    "images": ["AOTfigure3-2.png", "AOTfigure3-3.png", "AOTfigure3-4.png", "AOTfigure3-5.png"],
    "amount": 100,
    "animeName": "AttackOnTitan"
  },
  {
    "name": "Attack on Titan Levi Humanity's Strongest Soldier",
    "character": "Levi Ackerman",
    "company": "Attack on Titan",
    "price": 399,
    "dimensions": "24 cm",
    "material": "PVC",
    "brand": "Pony Canyon",
    "principalImage": "AOTfigure4-1.png",
    "images": ["AOTfigure4-2.png", "AOTfigure4-3.png", "AOTfigure4-4.png", "AOTfigure4-5.png"],
    "amount": 100,
    "animeName": "AttackOnTitan"
  },
  {
    "name": "Attack on Titan Armin Arlert: Colossus Titan",
    "character": "Titan Armin",
    "company": "Attack on Titan",
    "price": 80,
    "dimensions": "26 cm",
    "material": "PVC",
    "brand": "Pop Up Parade L",
    "principalImage": "AOTfigure5-1.png",
    "images": ["AOTfigure5-2.png", "AOTfigure5-3.png", "AOTfigure5-4.png", "AOTfigure5-5.png"],
    "amount": 100,
    "animeName": "AttackOnTitan"
  },
  {
    "name": "Shingeki no Kyojin Mikasa VS The Armored Titan",
    "character": "Mikasa Ackerman",
    "company": "Attack on Titan",
    "price": 700,
    "dimensions": "40x40x37 cm (alto x ancho x largo)",
    "material": "polystone, resina",
    "brand": "Oniri Creations",
    "principalImage": "AOTfigure6-1.png",
    "images": ["AOTfigure6-2.png", "AOTfigure6-3.png", "AOTfigure6-4.png", "AOTfigure6-5.png"],
    "amount": 100,
    "animeName": "AttackOnTitan"
  },
  {
    "name": "Shingeki no Kyojin Mikasa Ackerman",
    "character": "Mikasa Ackerman",
    "company": "Attack on Titan",
    "price": 659,
    "dimensions": "39x38x40 cm (alto x ancho x largo)",
    "material": "poliuretano, resina, PVC",
    "brand": "Kitsune Statue",
    "principalImage": "AOTfigure7-1.png",
    "images": ["AOTfigure7-2.png", "AOTfigure7-3.png", "AOTfigure7-4.png", "AOTfigure7-5.png"],
    "amount": 100,
    "animeName": "AttackOnTitan"
  },
  {
    "name": "Attack on Titan Mikasa Ackerman DX",
    "character": "Mikasa Ackerman",
    "company": "Attack on Titan",
    "price": 200,
    "dimensions": "28 cm",
    "material": "PVC",
    "brand": "Good Smile Company",
    "principalImage": "AOTfigure8-1.png",
    "images": ["AOTfigure8-2.png", "AOTfigure8-3.png", "AOTfigure8-4.png", "AOTfigure8-5.png"],
    "amount": 100,
    "animeName": "AttackOnTitan"
  },
  {
    "name": "The Female Titan vs The Attack Titan",
    "character": "The Female Titan",
    "company": "Attack on Titan",
    "price": 2200,
    "dimensions": "45 cm",
    "material": "resina",
    "brand": "Bandai",
    "principalImage": "AOTfigure9-1.png",
    "images": ["AOTfigure9-2.png", "AOTfigure9-3.png", "AOTfigure9-4.png", "AOTfigure9-5.png"],
    "amount": 100,
    "animeName": "AttackOnTitan"
  },
  {
    "name": "Attack Titan vs Armored Titan",
    "character": "Attack Titan",
    "company": "Attack on Titan",
    "price": 1959,
    "dimensions": "61x73x70 cm (alto x ancho x largo)",
    "material": "polystone, resina",
    "brand": "Figurama Collectors",
    "principalImage": "AOTfigure10-1.png",
    "images": ["AOTfigure10-2.png", "AOTfigure10-3.png", "AOTfigure10-4.png", "AOTfigure10-5.png"],
    "amount": 100,
    "animeName": "AttackOnTitan"
  }
]
