[
  {
    "name": "Midoriya, Bakugo & Todoroki Prime 1 Studio",
    "character": "Midoriya, Bakugo y Todoroki",
    "company": "My Hero Academia",
    "price": 2100,
    "dimensions": "69x57x55 cm (alto x ancho x largo)",
    "material": "polystone, resina",
    "brand": "Prime 1 Studio",
    "principalImage": "MyHeroAcademiaFigure1-1.png",
    "images": ["MyHeroAcademiaFigure1-2.png", "MyHeroAcademiaFigure1-3.png", "MyHeroAcademiaFigure1-4.png", "MyHeroAcademiaFigure1-5.png"],
    "amount": 100,
    "animeName": "MyHeroAcademia"
  },
  {
    "name": "Izuku Midoriya vs. Muscular",
    "character": "Izuku Midoriya",
    "company": "My Hero Academia",
    "price": 600,
    "dimensions": "30x29x21 cm (alto x ancho x largo)",
    "material": "PVC",
    "brand": "S-FIRE",
    "principalImage": "MyHeroAcademiaFigure2-1.png",
    "images": ["MyHeroAcademiaFigure2-2.png", "MyHeroAcademiaFigure2-3.png", "MyHeroAcademiaFigure2-4.png", "MyHeroAcademiaFigure2-5.png"],
    "amount": 100,
    "animeName": "MyHeroAcademia"
  },
  {
    "name": "Izuku Midoriya vs. Stain",
    "character": "Izuku Midoriya",
    "company": "My Hero Academia",
    "price": 539,
    "dimensions": "30 cm",
    "material": "PVC",
    "brand": "S-FIRE",
    "principalImage": "MyHeroAcademiaFigure3-1.png",
    "images": ["MyHeroAcademiaFigure3-2.png", "MyHeroAcademiaFigure3-3.png", "MyHeroAcademiaFigure3-4.png", "MyHeroAcademiaFigure3-5.png"],
    "amount": 100,
    "animeName": "MyHeroAcademia"
  },
  {
    "name": "Izuku Midoriya IKIGAI",
    "character": "Izuku Midoriya",
    "company": "My Hero Academia",
    "price": 400,
    "dimensions": "29x18x36 cm (alto x ancho x largo)",
    "material": "poliresina",
    "brand": "Tsume",
    "principalImage": "MyHeroAcademiaFigure4-1.png",
    "images": ["MyHeroAcademiaFigure4-2.png", "MyHeroAcademiaFigure4-3.png", "MyHeroAcademiaFigure4-4.png", "MyHeroAcademiaFigure4-5.png"],
    "amount": 100,
    "animeName": "MyHeroAcademia"
  },
  {
    "name": "Izuku Midoriya & Eri S-FIRE",
    "character": "Izuku Midoriya",
    "company": "My Hero Academia",
    "price": 490,
    "dimensions": "20x31x20 cm (alto x ancho x largo)",
    "material": "PVC",
    "brand": "SEGA",
    "principalImage": "MyHeroAcademiaFigure5-1.png",
    "images": ["MyHeroAcademiaFigure5-2.png", "MyHeroAcademiaFigure5-3.png", "MyHeroAcademiaFigure5-4.png", "MyHeroAcademiaFigure5-5.png"],
    "amount": 100,
    "animeName": "MyHeroAcademia"
  },
  {
    "name": "Izuku Midoriya Dark Deku",
    "character": "Izuku Midoriya",
    "company": "My Hero Academia",
    "price": 349,
    "dimensions": "29 cm",
    "material": "PVC",
    "brand": "Kotobukiya",
    "principalImage": "MyHeroAcademiaFigure6-1.png",
    "images": ["MyHeroAcademiaFigure6-2.png", "MyHeroAcademiaFigure6-3.png", "MyHeroAcademiaFigure6-4.png", "MyHeroAcademiaFigure6-5.png"],
    "amount": 100,
    "animeName": "MyHeroAcademia"
  },
  {
    "name": "Katsuki Bakugo IKIGAI",
    "character": "Katsuki Bakugo",
    "company": "My Hero Academia",
    "price": 389,
    "dimensions": "30x18x36 cm (alto x ancho x largo)",
    "material": "poliresina",
    "brand": "Tsume",
    "principalImage": "MyHeroAcademiaFigure7-1.png",
    "images": ["MyHeroAcademiaFigure7-2.png", "MyHeroAcademiaFigure7-3.png", "MyHeroAcademiaFigure7-4.png", "MyHeroAcademiaFigure7-5.png"],
    "amount": 100,
    "animeName": "MyHeroAcademia"
  },
  {
    "name": "Endeavor IKIGAI",
    "character": "Endeavor",
    "company": "My Hero Academia",
    "price": 389,
    "dimensions": "37x18x36 cm (alto x ancho x largo)",
    "material": "poliresina",
    "brand": "Tsume",
    "principalImage": "MyHeroAcademiaFigure8-1.png",
    "images": ["MyHeroAcademiaFigure8-2.png", "MyHeroAcademiaFigure8-3.png", "MyHeroAcademiaFigure8-4.png", "MyHeroAcademiaFigure8-5.png"],
    "amount": 100,
    "animeName": "MyHeroAcademia"
  },
  {
    "name": "Shoto Todoroki IKIGAI",
    "character": "Shoto Todoroki",
    "company": "My Hero Academia",
    "price": 439,
    "dimensions": "34x18x36 cm (alto x ancho x largo)",
    "material": "poliresina",
    "brand": "Tsume",
    "principalImage": "MyHeroAcademiaFigure9-1.png",
    "images": ["MyHeroAcademiaFigure9-2.png", "MyHeroAcademiaFigure9-3.png", "MyHeroAcademiaFigure9-4.png", "MyHeroAcademiaFigure9-5.png"],
    "amount": 100,
    "animeName": "MyHeroAcademia"
  },
  {
    "name": "All Might S-FIRE",
    "character": "All Might",
    "company": "My Hero Academia",
    "price": 269,
    "dimensions": "20 cm",
    "material": "PVC",
    "brand": "SEGA",
    "principalImage": "MyHeroAcademiaFigure10-1.png",
    "images": ["MyHeroAcademiaFigure10-2.png", "MyHeroAcademiaFigure10-3.png", "MyHeroAcademiaFigure10-4.png", "MyHeroAcademiaFigure10-5.png"],
    "amount": 100,
    "animeName": "MyHeroAcademia"
  }
]
